{"users":[{"id":7262,"username":"Alex78H","avatar_template":"/user_avatar/forums.whonix.org/alex78h/{size}/3315_2.png","flair_name":null,"trust_level":0},{"id":6141,"username":"nyxnor","avatar_template":"/user_avatar/forums.whonix.org/nyxnor/{size}/2874_2.png","flair_name":null,"trust_level":2},{"id":3,"username":"Patrick","avatar_template":"/user_avatar/forums.whonix.org/patrick/{size}/2848_2.png","flair_name":null,"admin":true,"moderator":true,"trust_level":4},{"id":7210,"username":"athread4","avatar_template":"/letter_avatar_proxy/v4/letter/a/e47c2d/{size}.png","flair_name":null,"trust_level":1},{"id":5099,"username":"numeroustranslate","avatar_template":"/letter_avatar_proxy/v4/letter/n/d6d6ee/{size}.png","flair_name":null,"trust_level":2},{"id":7202,"username":"SecOps","avatar_template":"/letter_avatar_proxy/v4/letter/s/f05b48/{size}.png","flair_name":null,"trust_level":0},{"id":7184,"username":"captainyorshka","avatar_template":"/letter_avatar_proxy/v4/letter/c/ac91a4/{size}.png","flair_name":null,"trust_level":0},{"id":7178,"username":"anon12802191","avatar_template":"/letter_avatar_proxy/v4/letter/a/f0a364/{size}.png","flair_name":null,"trust_level":1},{"id":7116,"username":"zenix","avatar_template":"/letter_avatar_proxy/v4/letter/z/9dc877/{size}.png","flair_name":null,"trust_level":0},{"id":7174,"username":"grrrr","avatar_template":"/letter_avatar_proxy/v4/letter/g/8c91f0/{size}.png","flair_name":null,"trust_level":0},{"id":7148,"username":"gonein5","avatar_template":"/letter_avatar_proxy/v4/letter/g/f07891/{size}.png","flair_name":null,"trust_level":1},{"id":6029,"username":"midge","avatar_template":"/letter_avatar_proxy/v4/letter/m/59ef9b/{size}.png","flair_name":null,"trust_level":1},{"id":4231,"username":"anonimac","avatar_template":"/letter_avatar_proxy/v4/letter/a/d9b06d/{size}.png","flair_name":null,"trust_level":1},{"id":410,"username":"TNT_BOM_BOM","avatar_template":"/user_avatar/forums.whonix.org/tnt_bom_bom/{size}/2148_2.png","flair_name":null,"trust_level":2},{"id":6484,"username":"adam3424","avatar_template":"/letter_avatar_proxy/v4/letter/a/cdc98d/{size}.png","flair_name":null,"trust_level":0},{"id":6962,"username":"metalworker","avatar_template":"/letter_avatar_proxy/v4/letter/m/f19dbf/{size}.png","flair_name":null,"trust_level":0},{"id":6698,"username":"bumlapuspi","avatar_template":"/letter_avatar_proxy/v4/letter/b/db5fbb/{size}.png","flair_name":null,"trust_level":0},{"id":6379,"username":"cad","avatar_template":"/letter_avatar_proxy/v4/letter/c/76d3ee/{size}.png","flair_name":null,"trust_level":0},{"id":6476,"username":"rando","avatar_template":"/letter_avatar_proxy/v4/letter/r/0ea827/{size}.png","flair_name":null,"trust_level":2},{"id":5799,"username":"Jondoesnowden","avatar_template":"/letter_avatar_proxy/v4/letter/j/848f3c/{size}.png","flair_name":null,"trust_level":0},{"id":5326,"username":"PhoenixRising","avatar_template":"/letter_avatar_proxy/v4/letter/p/6f9a4e/{size}.png","flair_name":null,"trust_level":0},{"id":5272,"username":"Komms","avatar_template":"/letter_avatar_proxy/v4/letter/k/919ad9/{size}.png","flair_name":null,"trust_level":2},{"id":6466,"username":"x99x","avatar_template":"/letter_avatar_proxy/v4/letter/x/ec9cab/{size}.png","flair_name":null,"trust_level":1},{"id":6261,"username":"Dizzy49","avatar_template":"/letter_avatar_proxy/v4/letter/d/edb3f5/{size}.png","flair_name":null,"trust_level":0},{"id":6441,"username":"0x1f","avatar_template":"/user_avatar/forums.whonix.org/0x1f/{size}/2975_2.png","flair_name":null,"trust_level":1},{"id":6429,"username":"Evo0","avatar_template":"/letter_avatar_proxy/v4/letter/e/49beb7/{size}.png","flair_name":null,"trust_level":0},{"id":6143,"username":"jackson","avatar_template":"/letter_avatar_proxy/v4/letter/j/e68b1a/{size}.png","flair_name":null,"trust_level":0},{"id":4216,"username":"124Freibier","avatar_template":"/letter_avatar_proxy/v4/letter/1/58956e/{size}.png","flair_name":null,"trust_level":0},{"id":4221,"username":"WhoDat22","avatar_template":"/letter_avatar_proxy/v4/letter/w/a183cd/{size}.png","flair_name":null,"trust_level":0},{"id":2641,"username":"0brand","avatar_template":"/letter_avatar_proxy/v4/letter/0/ec9cab/{size}.png","flair_name":null,"trust_level":2},{"id":4337,"username":"infosecwriter","avatar_template":"/letter_avatar_proxy/v4/letter/i/5f9b8f/{size}.png","flair_name":null,"trust_level":0},{"id":6259,"username":"RobertT","avatar_template":"/letter_avatar_proxy/v4/letter/r/dec6dc/{size}.png","flair_name":null,"trust_level":0},{"id":6304,"username":"Andrew","avatar_template":"/letter_avatar_proxy/v4/letter/a/f19dbf/{size}.png","flair_name":null,"trust_level":0},{"id":3765,"username":"Fullof","avatar_template":"/letter_avatar_proxy/v4/letter/f/5fc32e/{size}.png","flair_name":null,"trust_level":0},{"id":6390,"username":"ScratchedSkateboard","avatar_template":"/letter_avatar_proxy/v4/letter/s/9de053/{size}.png","flair_name":null,"trust_level":0},{"id":6378,"username":"lattt","avatar_template":"/letter_avatar_proxy/v4/letter/l/8c91f0/{size}.png","flair_name":null,"trust_level":1},{"id":75,"username":"HulaHoop","avatar_template":"/letter_avatar_proxy/v4/letter/h/edb3f5/{size}.png","flair_name":null,"admin":true,"moderator":true,"trust_level":4},{"id":4609,"username":"Patrick_mobile","avatar_template":"/letter_avatar_proxy/v4/letter/p/898d66/{size}.png","flair_name":null,"trust_level":2},{"id":4419,"username":"madaidan","avatar_template":"/letter_avatar_proxy/v4/letter/m/ea5d25/{size}.png","flair_name":null,"trust_level":2},{"id":6322,"username":"gelapir","avatar_template":"/letter_avatar_proxy/v4/letter/g/f475e1/{size}.png","flair_name":null,"trust_level":1}],"primary_groups":[],"flair_groups":[],"topic_list":{"can_create_topic":false,"more_topics_url":"/c/virtualbox/16?page=1","per_page":30,"top_tags":[],"topics":[{"id":16117,"title":"Cloning old gateway, but password is different?","fancy_title":"Cloning old gateway, but password is different?","slug":"cloning-old-gateway-but-password-is-different","posts_count":9,"reply_count":5,"highest_post_number":10,"image_url":null,"created_at":"2022-12-12T07:10:15.203Z","last_posted_at":"2022-12-15T01:22:24.188Z","bumped":true,"bumped_at":"2022-12-15T01:22:24.188Z","archetype":"regular","unseen":false,"pinned":false,"unpinned":null,"excerpt":"I’d full cloned whonix gateway &amp; workstation in virtualbox (with new MAC address) for onionshare. After creating 2 new internal networks for the clones however, when adding sudo onion-grater-add 40_onionshare into gatewa&hellip;","visible":true,"closed":false,"archived":false,"bookmarked":null,"liked":null,"tags":[],"tags_descriptions":{},"views":22,"like_count":1,"has_summary":false,"last_poster_username":"Alex78H","category_id":16,"pinned_globally":false,"featured_link":null,"posters":[{"extras":"latest","description":"Original Poster, Most Recent Poster","user_id":7262,"primary_group_id":null,"flair_group_id":null},{"extras":null,"description":"Frequent Poster","user_id":6141,"primary_group_id":null,"flair_group_id":null},{"extras":null,"description":"Frequent Poster","user_id":3,"primary_group_id":null,"flair_group_id":null}]},{"id":15997,"title":"Two question about slow speed and antivirus.","fancy_title":"Two question about slow speed and antivirus.","slug":"two-question-about-slow-speed-and-antivirus","posts_count":4,"reply_count":1,"highest_post_number":4,"image_url":null,"created_at":"2022-11-20T18:28:33.000Z","last_posted_at":"2022-12-08T17:28:24.020Z","bumped":true,"bumped_at":"2022-12-08T17:28:24.020Z","archetype":"regular","unseen":false,"pinned":false,"unpinned":null,"excerpt":"Hello i have two question about WHONIX. \n1 - Is it normal that for exemple update for TOR have non stop 100kb-50kb/s? is this speed isn’t too slow? \n2- Does it make sense and is it possible to install antyvirus for exemp&hellip;","visible":true,"closed":false,"archived":false,"bookmarked":null,"liked":null,"tags":[],"tags_descriptions":{},"views":89,"like_count":3,"has_summary":false,"last_poster_username":"Patrick","category_id":16,"pinned_globally":false,"featured_link":null,"posters":[{"extras":null,"description":"Original Poster","user_id":7210,"primary_group_id":null,"flair_group_id":null},{"extras":null,"description":"Frequent Poster","user_id":5099,"primary_group_id":null,"flair_group_id":null},{"extras":"latest","description":"Most Recent Poster","user_id":3,"primary_group_id":null,"flair_group_id":null}]},{"id":15971,"title":"Difference between whonix gateway and workstation? What is needed for kali","fancy_title":"Difference between whonix gateway and workstation? What is needed for kali","slug":"difference-between-whonix-gateway-and-workstation-what-is-needed-for-kali","posts_count":3,"reply_count":0,"highest_post_number":3,"image_url":null,"created_at":"2022-11-17T04:10:25.889Z","last_posted_at":"2022-11-17T14:12:14.206Z","bumped":true,"bumped_at":"2022-11-17T14:12:10.172Z","archetype":"regular","unseen":false,"pinned":false,"unpinned":null,"excerpt":"So was trying to set up Kali to run through whonix on virtualbox.  I downloaded whonix XFCE linux for VBOX and imported it into virtualbox.  Once that is done can i get rid of the workstation since i would just be using &hellip;","visible":true,"closed":true,"archived":false,"bookmarked":null,"liked":null,"tags":[],"tags_descriptions":{},"views":69,"like_count":0,"has_summary":false,"last_poster_username":"Patrick","category_id":16,"pinned_globally":false,"featured_link":null,"posters":[{"extras":null,"description":"Original Poster","user_id":7202,"primary_group_id":null,"flair_group_id":null},{"extras":"latest","description":"Most Recent Poster","user_id":3,"primary_group_id":null,"flair_group_id":null}]},{"id":15927,"title":"Whonix aborted error","fancy_title":"Whonix aborted error","slug":"whonix-aborted-error","posts_count":2,"reply_count":0,"highest_post_number":2,"image_url":null,"created_at":"2022-11-06T22:11:00.907Z","last_posted_at":"2022-11-07T20:07:20.583Z","bumped":true,"bumped_at":"2022-11-07T20:07:20.583Z","archetype":"regular","unseen":false,"pinned":false,"unpinned":null,"excerpt":"hi, first time trying to run whonix, I wanted to try whonix through virtual machine but it keeps saying aborted and it won’t run, how do I fix this?","visible":true,"closed":false,"archived":false,"bookmarked":null,"liked":null,"tags":[],"tags_descriptions":{},"views":112,"like_count":0,"has_summary":false,"last_poster_username":"Patrick","category_id":16,"pinned_globally":false,"featured_link":null,"posters":[{"extras":null,"description":"Original Poster","user_id":7184,"primary_group_id":null,"flair_group_id":null},{"extras":"latest","description":"Most Recent Poster","user_id":3,"primary_group_id":null,"flair_group_id":null}]},{"id":15923,"title":"How to disable DHCP","fancy_title":"How to disable DHCP","slug":"how-to-disable-dhcp","posts_count":2,"reply_count":0,"highest_post_number":2,"image_url":null,"created_at":"2022-11-06T14:51:24.315Z","last_posted_at":"2022-11-07T19:45:32.205Z","bumped":true,"bumped_at":"2022-11-07T19:45:32.205Z","archetype":"regular","unseen":false,"pinned":false,"unpinned":null,"excerpt":"How to disable DHCP in Whonix Virtualbox?","visible":true,"closed":false,"archived":false,"bookmarked":null,"liked":null,"tags":[],"tags_descriptions":{},"views":110,"like_count":0,"has_summary":false,"last_poster_username":"Patrick","category_id":16,"pinned_globally":false,"featured_link":null,"posters":[{"extras":null,"description":"Original Poster","user_id":7178,"primary_group_id":null,"flair_group_id":null},{"extras":"latest","description":"Most Recent Poster","user_id":3,"primary_group_id":null,"flair_group_id":null}]},{"id":15666,"title":"A lot of package hash mismatches when trying to update new system","fancy_title":"A lot of package hash mismatches when trying to update new system","slug":"a-lot-of-package-hash-mismatches-when-trying-to-update-new-system","posts_count":4,"reply_count":0,"highest_post_number":4,"image_url":null,"created_at":"2022-10-03T06:38:02.958Z","last_posted_at":"2022-11-02T13:38:50.854Z","bumped":true,"bumped_at":"2022-11-02T13:38:50.854Z","archetype":"regular","unseen":false,"pinned":false,"unpinned":null,"excerpt":"Whonix installed from Whonix-XFCE-16.0.5.3.ova \nFirst run of Whonix Gateway \nFirst system update \nsudo apt dist-upgrade (after sudo apt update, which succeeds, see other topic about random segfaults) produces a lot of ha&hellip;","visible":true,"closed":false,"archived":false,"bookmarked":null,"liked":null,"tags":[],"tags_descriptions":{},"views":189,"like_count":0,"has_summary":false,"last_poster_username":"Patrick","category_id":16,"pinned_globally":false,"featured_link":null,"posters":[{"extras":null,"description":"Original Poster","user_id":7116,"primary_group_id":null,"flair_group_id":null},{"extras":null,"description":"Frequent Poster","user_id":7174,"primary_group_id":null,"flair_group_id":null},{"extras":"latest","description":"Most Recent Poster","user_id":3,"primary_group_id":null,"flair_group_id":null}]},{"id":15848,"title":"VirtualBox 7.0.0 not compatible with Whonix on macOS hosts","fancy_title":"VirtualBox 7.0.0 not compatible with Whonix on macOS hosts","slug":"virtualbox-7-0-0-not-compatible-with-whonix-on-macos-hosts","posts_count":3,"reply_count":0,"highest_post_number":3,"image_url":null,"created_at":"2022-10-19T14:33:13.904Z","last_posted_at":"2022-10-20T20:42:52.608Z","bumped":true,"bumped_at":"2022-10-20T20:42:52.608Z","archetype":"regular","unseen":false,"pinned":false,"unpinned":null,"excerpt":"From the changelog: \n\nmacOS host: Dropped all kernel extensions. VirtualBox relies fully on the hypervisor and vmnet frameworks provided by Apple now. At the moment the implementation lacks “Internal Networking” function&hellip;","visible":true,"closed":false,"archived":false,"bookmarked":null,"liked":null,"tags":[],"tags_descriptions":{},"views":162,"like_count":3,"has_summary":false,"last_poster_username":"gonein5","category_id":16,"pinned_globally":false,"featured_link":null,"posters":[{"extras":"latest","description":"Original Poster, Most Recent Poster","user_id":7148,"primary_group_id":null,"flair_group_id":null},{"extras":null,"description":"Frequent Poster","user_id":3,"primary_group_id":null,"flair_group_id":null}]},{"id":15664,"title":"Random segfaults when updating a new install","fancy_title":"Random segfaults when updating a new install","slug":"random-segfaults-when-updating-a-new-install","posts_count":2,"reply_count":0,"highest_post_number":2,"image_url":null,"created_at":"2022-10-03T05:24:02.281Z","last_posted_at":"2022-10-03T07:55:33.773Z","bumped":true,"bumped_at":"2022-10-03T07:55:33.773Z","archetype":"regular","unseen":false,"pinned":false,"unpinned":null,"excerpt":"Whonix installed from Whonix-XFCE-16.0.5.3.ova \nFirst run of Whonix Gateway \nFirst system update \nsudo apt update  randomly segfaults","visible":true,"closed":false,"archived":false,"bookmarked":null,"liked":null,"tags":[],"tags_descriptions":{},"views":179,"like_count":0,"has_summary":false,"last_poster_username":"Patrick","category_id":16,"pinned_globally":false,"featured_link":null,"posters":[{"extras":null,"description":"Original Poster","user_id":7116,"primary_group_id":null,"flair_group_id":null},{"extras":"latest","description":"Most Recent Poster","user_id":3,"primary_group_id":null,"flair_group_id":null}]},{"id":13767,"title":"Tor Browser crashing in Whonix VirtualBox since upgrade to Host Linux Kernel version 5.10.0-15","fancy_title":"Tor Browser crashing in Whonix VirtualBox since upgrade to Host Linux Kernel version 5.10.0-15","slug":"tor-browser-crashing-in-whonix-virtualbox-since-upgrade-to-host-linux-kernel-version-5-10-0-15","posts_count":51,"reply_count":19,"highest_post_number":53,"image_url":null,"created_at":"2022-06-12T00:07:55.786Z","last_posted_at":"2022-09-26T21:03:18.895Z","bumped":true,"bumped_at":"2022-09-26T21:03:18.895Z","archetype":"regular","unseen":false,"pinned":false,"unpinned":null,"excerpt":"I have an issue with Tor Browser crashing in Whonix in debian virtualbox. \nThe issue seems to be whonix related as I did the following after it started crashing: \n\nI upgraded debian to the latest. (only TZDATA needed upg&hellip;","visible":true,"closed":false,"archived":false,"bookmarked":null,"liked":null,"tags":[],"tags_descriptions":{},"views":617,"like_count":11,"has_summary":true,"last_poster_username":"Patrick","category_id":16,"pinned_globally":false,"featured_link":null,"posters":[{"extras":null,"description":"Original Poster","user_id":6029,"primary_group_id":null,"flair_group_id":null},{"extras":null,"description":"Frequent Poster","user_id":4231,"primary_group_id":null,"flair_group_id":null},{"extras":null,"description":"Frequent Poster","user_id":410,"primary_group_id":null,"flair_group_id":null},{"extras":null,"description":"Frequent Poster","user_id":6484,"primary_group_id":null,"flair_group_id":null},{"extras":"latest","description":"Most Recent Poster","user_id":3,"primary_group_id":null,"flair_group_id":null}]},{"id":15262,"title":"Ledger not detected in VirtualBox on Linux","fancy_title":"Ledger not detected in VirtualBox on Linux","slug":"ledger-not-detected-in-virtualbox-on-linux","posts_count":4,"reply_count":1,"highest_post_number":4,"image_url":null,"created_at":"2022-09-12T11:27:50.252Z","last_posted_at":"2022-09-25T08:42:25.395Z","bumped":true,"bumped_at":"2022-09-25T08:42:25.395Z","archetype":"regular","unseen":false,"pinned":false,"unpinned":null,"excerpt":"Hello, \nI am trying to use Ledger + VirtualBox + Whonix and when I try to connect the Ledger to Whonix in VirtualBox settings, I get “No device available” message. \nVersion details: \n\nLedger Nano X, firmware and apps up &hellip;","visible":true,"closed":false,"archived":false,"bookmarked":null,"liked":null,"tags":[],"tags_descriptions":{},"views":230,"like_count":0,"has_summary":false,"last_poster_username":"Patrick","category_id":16,"pinned_globally":false,"featured_link":null,"posters":[{"extras":null,"description":"Original Poster","user_id":6962,"primary_group_id":null,"flair_group_id":null},{"extras":"latest","description":"Most Recent Poster","user_id":3,"primary_group_id":null,"flair_group_id":null}]},{"id":14505,"title":"Creating a double tor chain","fancy_title":"Creating a double tor chain","slug":"creating-a-double-tor-chain","posts_count":2,"reply_count":0,"highest_post_number":2,"image_url":null,"created_at":"2022-08-15T17:01:02.282Z","last_posted_at":"2022-08-15T17:01:52.619Z","bumped":true,"bumped_at":"2022-08-15T17:01:52.619Z","archetype":"regular","unseen":false,"pinned":false,"unpinned":null,"excerpt":"I have two sets of whoinix installed. I need to make sure that gateway2 from the second set takes the Internet from gateway1. That is, make the chain tor → tor.","visible":true,"closed":false,"archived":false,"bookmarked":null,"liked":null,"tags":[],"tags_descriptions":{},"views":291,"like_count":0,"has_summary":false,"last_poster_username":"Patrick","category_id":16,"pinned_globally":false,"featured_link":null,"posters":[{"extras":null,"description":"Original Poster","user_id":6698,"primary_group_id":null,"flair_group_id":null},{"extras":"latest","description":"Most Recent Poster","user_id":3,"primary_group_id":null,"flair_group_id":null}]},{"id":14462,"title":"Whonix-Custom-Workstation EFI Booting","fancy_title":"Whonix-Custom-Workstation EFI Booting","slug":"whonix-custom-workstation-efi-booting","posts_count":8,"reply_count":2,"highest_post_number":8,"image_url":null,"created_at":"2022-08-12T00:55:43.000Z","last_posted_at":"2022-08-12T16:58:12.000Z","bumped":true,"bumped_at":"2022-08-12T16:58:12.000Z","archetype":"regular","unseen":false,"pinned":false,"unpinned":null,"excerpt":"I followed the procedure but I can’t seem to get it to boot with efi. Im using an arch Linux iso with virtual box.","visible":true,"closed":false,"archived":false,"bookmarked":null,"liked":null,"tags":[],"tags_descriptions":{},"views":289,"like_count":0,"has_summary":false,"last_poster_username":"cad","category_id":16,"pinned_globally":false,"featured_link":null,"posters":[{"extras":"latest","description":"Original Poster, Most Recent Poster","user_id":6379,"primary_group_id":null,"flair_group_id":null},{"extras":null,"description":"Frequent Poster","user_id":3,"primary_group_id":null,"flair_group_id":null},{"extras":null,"description":"Frequent Poster","user_id":6476,"primary_group_id":null,"flair_group_id":null}]},{"id":13813,"title":"Core Isolation in Windows 10 breaks Whonix","fancy_title":"Core Isolation in Windows 10 breaks Whonix","slug":"core-isolation-in-windows-10-breaks-whonix","posts_count":8,"reply_count":2,"highest_post_number":8,"image_url":null,"created_at":"2022-06-19T22:23:45.157Z","last_posted_at":"2022-08-04T14:57:29.798Z","bumped":true,"bumped_at":"2022-08-04T14:57:29.798Z","archetype":"regular","unseen":false,"pinned":false,"unpinned":null,"excerpt":"Core Isolation in Windows 10 breaks Whonix in several ways. \nDoes anybody know if this is a Whonix problem or a VirtualBox problem? \nWhen having Core isolation activated I get problems with: \nBooting, I get an error stat&hellip;","visible":true,"closed":false,"archived":false,"bookmarked":null,"liked":null,"tags":[],"tags_descriptions":{},"views":458,"like_count":6,"has_summary":false,"last_poster_username":"TNT_BOM_BOM","category_id":16,"pinned_globally":false,"featured_link":null,"posters":[{"extras":null,"description":"Original Poster","user_id":5799,"primary_group_id":null,"flair_group_id":null},{"extras":null,"description":"Frequent Poster","user_id":3,"primary_group_id":null,"flair_group_id":null},{"extras":"latest","description":"Most Recent Poster","user_id":410,"primary_group_id":null,"flair_group_id":null}]},{"id":14221,"title":"whonix 16.0.5.3 refuses to start on virtualbox 6.1.36.","fancy_title":"whonix 16.0.5.3 refuses to start on virtualbox 6.1.36.","slug":"whonix-16-0-5-3-refuses-to-start-on-virtualbox-6-1-36","posts_count":3,"reply_count":1,"highest_post_number":3,"image_url":null,"created_at":"2022-07-23T09:44:16.223Z","last_posted_at":"2022-07-30T05:51:50.656Z","bumped":true,"bumped_at":"2022-07-30T05:58:06.456Z","archetype":"regular","unseen":false,"pinned":false,"unpinned":null,"excerpt":"Everything that is to be said I have said on title. Using Windows.","visible":true,"closed":false,"archived":false,"bookmarked":null,"liked":null,"tags":[],"tags_descriptions":{},"views":347,"like_count":2,"has_summary":false,"last_poster_username":"PhoenixRising","category_id":16,"pinned_globally":false,"featured_link":null,"posters":[{"extras":"latest","description":"Original Poster, Most Recent Poster","user_id":5326,"primary_group_id":null,"flair_group_id":null},{"extras":null,"description":"Frequent Poster","user_id":3,"primary_group_id":null,"flair_group_id":null}]},{"id":14200,"title":"CLI vs GUI difference","fancy_title":"CLI vs GUI difference","slug":"cli-vs-gui-difference","posts_count":2,"reply_count":0,"highest_post_number":2,"image_url":null,"created_at":"2022-07-21T15:54:43.994Z","last_posted_at":"2022-07-21T18:12:57.304Z","bumped":true,"bumped_at":"2022-07-21T18:12:57.304Z","archetype":"regular","unseen":false,"pinned":false,"unpinned":null,"excerpt":"Can someone explain the difference between the CLI vs GUI. \nIn past times on a windows host I have used VB so I am familiar. \n\n\n\n\nNow on linux host I am already running the kvm Virt Manager with windows guest isntalled. &hellip;","visible":true,"closed":false,"archived":false,"bookmarked":null,"liked":null,"tags":[],"tags_descriptions":{},"views":363,"like_count":0,"has_summary":false,"last_poster_username":"Patrick","category_id":16,"pinned_globally":false,"featured_link":null,"posters":[{"extras":null,"description":"Original Poster","user_id":5272,"primary_group_id":null,"flair_group_id":null},{"extras":"latest","description":"Most Recent Poster","user_id":3,"primary_group_id":null,"flair_group_id":null}]},{"id":14186,"title":"Tor browser crashing and whonix glitching","fancy_title":"Tor browser crashing and whonix glitching","slug":"tor-browser-crashing-and-whonix-glitching","posts_count":2,"reply_count":0,"highest_post_number":2,"image_url":null,"created_at":"2022-07-19T04:59:21.344Z","last_posted_at":"2022-07-19T07:45:53.320Z","bumped":true,"bumped_at":"2022-07-19T07:45:53.320Z","archetype":"regular","unseen":false,"pinned":false,"unpinned":null,"excerpt":"Hoping someone could help. \nI have installed Virtualbox as per the instructions here: \nhttps://www.whonix.org/wiki/VirtualBox/Recommended_Version \n\n\nI am running the latest kicksecure as my host on bare metal \nAlso Runni&hellip;","visible":true,"closed":false,"archived":false,"bookmarked":null,"liked":null,"tags":[],"tags_descriptions":{},"views":365,"like_count":0,"has_summary":false,"last_poster_username":"Patrick","category_id":16,"pinned_globally":false,"featured_link":null,"posters":[{"extras":null,"description":"Original Poster","user_id":6466,"primary_group_id":null,"flair_group_id":null},{"extras":"latest","description":"Most Recent Poster","user_id":3,"primary_group_id":null,"flair_group_id":null}]},{"id":13436,"title":"Black Screen on Boot","fancy_title":"Black Screen on Boot","slug":"black-screen-on-boot","posts_count":8,"reply_count":3,"highest_post_number":8,"image_url":null,"created_at":"2022-03-11T10:16:37.394Z","last_posted_at":"2022-06-28T10:41:41.457Z","bumped":true,"bumped_at":"2022-06-28T10:41:41.457Z","archetype":"regular","unseen":false,"pinned":false,"unpinned":null,"excerpt":"I installed Whonix-XFCE 15.0.1.9.3 back in August and it’s been running great until a couple weeks ago. \nNow both the Gateway and Workstation boot to black screen.  They start to load, and after it gets to Loading Ramdis&hellip;","visible":true,"closed":false,"archived":false,"bookmarked":null,"liked":null,"tags":[],"tags_descriptions":{},"views":648,"like_count":1,"has_summary":false,"last_poster_username":"Patrick","category_id":16,"pinned_globally":false,"featured_link":null,"posters":[{"extras":null,"description":"Original Poster","user_id":6261,"primary_group_id":null,"flair_group_id":null},{"extras":null,"description":"Frequent Poster","user_id":6441,"primary_group_id":null,"flair_group_id":null},{"extras":"latest","description":"Most Recent Poster","user_id":3,"primary_group_id":null,"flair_group_id":null}]},{"id":12555,"title":"VBoxHardenedLoader","fancy_title":"VBoxHardenedLoader","slug":"vboxhardenedloader","posts_count":4,"reply_count":0,"highest_post_number":4,"image_url":null,"created_at":"2021-10-12T11:17:58.352Z","last_posted_at":"2022-06-27T23:53:05.036Z","bumped":true,"bumped_at":"2022-06-27T23:53:05.036Z","archetype":"regular","unseen":false,"pinned":false,"unpinned":null,"excerpt":"Hello developers. Question - is VBoxHardenedLoader compatible with Whonix? \nVBoxHardenedLoader is completely incompatible with Whonix, any change in accordance with the instructions will violate anonymity. \nVBoxHardenedL&hellip;","visible":true,"closed":false,"archived":false,"bookmarked":null,"liked":null,"tags":[],"tags_descriptions":{},"views":813,"like_count":0,"has_summary":false,"last_poster_username":"0x1f","category_id":16,"pinned_globally":false,"featured_link":null,"posters":[{"extras":null,"description":"Original Poster","user_id":5099,"primary_group_id":null,"flair_group_id":null},{"extras":null,"description":"Frequent Poster","user_id":3,"primary_group_id":null,"flair_group_id":null},{"extras":"latest","description":"Most Recent Poster","user_id":6441,"primary_group_id":null,"flair_group_id":null}]},{"id":13828,"title":"How worried should I be about a VM escape?","fancy_title":"How worried should I be about a VM escape?","slug":"how-worried-should-i-be-about-a-vm-escape","posts_count":3,"reply_count":0,"highest_post_number":3,"image_url":null,"created_at":"2022-06-22T16:48:49.764Z","last_posted_at":"2022-06-27T23:46:37.737Z","bumped":true,"bumped_at":"2022-06-27T23:46:37.737Z","archetype":"regular","unseen":false,"pinned":false,"unpinned":null,"excerpt":"Hiya! \nAs the title says, im confused about how worried i should be about VM escapes, is there anyway I can mitigate this? \nMany thanks &lt;3","visible":true,"closed":false,"archived":false,"bookmarked":null,"liked":null,"tags":[],"tags_descriptions":{},"views":415,"like_count":1,"has_summary":false,"last_poster_username":"0x1f","category_id":16,"pinned_globally":false,"featured_link":null,"posters":[{"extras":null,"description":"Original Poster","user_id":6429,"primary_group_id":null,"flair_group_id":null},{"extras":null,"description":"Frequent Poster","user_id":3,"primary_group_id":null,"flair_group_id":null},{"extras":"latest","description":"Most Recent Poster","user_id":6441,"primary_group_id":null,"flair_group_id":null}]},{"id":13170,"title":"VPN on Host System?","fancy_title":"VPN on Host System?","slug":"vpn-on-host-system","posts_count":3,"reply_count":0,"highest_post_number":3,"image_url":null,"created_at":"2022-01-09T23:31:57.331Z","last_posted_at":"2022-06-27T23:39:42.488Z","bumped":true,"bumped_at":"2022-06-27T23:39:42.488Z","archetype":"regular","unseen":false,"pinned":false,"unpinned":null,"excerpt":"I understand using a VPN in Whonix isnt entirely reccomended. \nWhat about running a VPN in the host system that isnt attached to the name? Does this pose the same risks as setting a VPN up after the tor connection inside&hellip;","visible":true,"closed":false,"archived":false,"bookmarked":null,"liked":null,"tags":[],"tags_descriptions":{},"views":669,"like_count":0,"has_summary":false,"last_poster_username":"0x1f","category_id":16,"pinned_globally":false,"featured_link":null,"posters":[{"extras":null,"description":"Original Poster","user_id":6143,"primary_group_id":null,"flair_group_id":null},{"extras":null,"description":"Frequent Poster","user_id":3,"primary_group_id":null,"flair_group_id":null},{"extras":"latest","description":"Most Recent Poster","user_id":6441,"primary_group_id":null,"flair_group_id":null}]},{"id":6755,"title":"Whonix starts first, but after first Screen - Blackscreen","fancy_title":"Whonix starts first, but after first Screen - Blackscreen","slug":"whonix-starts-first-but-after-first-screen-blackscreen","posts_count":11,"reply_count":4,"highest_post_number":11,"image_url":null,"created_at":"2019-01-29T20:36:53.529Z","last_posted_at":"2022-06-27T23:29:41.846Z","bumped":true,"bumped_at":"2022-06-27T23:29:41.846Z","archetype":"regular","unseen":false,"pinned":false,"unpinned":null,"excerpt":"Hi, \nevery time i want to start Whonix, it starts in Normal mode, loads only 2 things (RAM and something other) and then there is blackscreen. This on gateaway and workstation. And I cant shut it down, only close. \nDoes &hellip;","visible":true,"closed":false,"archived":false,"bookmarked":null,"liked":null,"tags":[],"tags_descriptions":{},"views":3262,"like_count":5,"has_summary":false,"last_poster_username":"0x1f","category_id":16,"pinned_globally":false,"featured_link":null,"posters":[{"extras":null,"description":"Original Poster","user_id":4216,"primary_group_id":null,"flair_group_id":null},{"extras":null,"description":"Frequent Poster","user_id":4221,"primary_group_id":null,"flair_group_id":null},{"extras":null,"description":"Frequent Poster","user_id":2641,"primary_group_id":null,"flair_group_id":null},{"extras":null,"description":"Frequent Poster","user_id":4337,"primary_group_id":null,"flair_group_id":null},{"extras":"latest","description":"Most Recent Poster","user_id":6441,"primary_group_id":null,"flair_group_id":null}]},{"id":13432,"title":"VM machines are much slower on Linux Mint than on WIndows 10","fancy_title":"VM machines are much slower on Linux Mint than on WIndows 10","slug":"vm-machines-are-much-slower-on-linux-mint-than-on-windows-10","posts_count":3,"reply_count":0,"highest_post_number":3,"image_url":null,"created_at":"2022-03-08T06:47:39.015Z","last_posted_at":"2022-06-27T23:10:28.392Z","bumped":true,"bumped_at":"2022-06-27T23:10:28.392Z","archetype":"regular","unseen":false,"pinned":false,"unpinned":null,"excerpt":"Hi! \nI have the latest Whonix-Gateway and Whonix-Workstation VMs on an SSD, which is connected to my PC via USB3.0 ports. Also I use and upgrate/update them frequently, so the systems are up to date. My problem is, that &hellip;","visible":true,"closed":false,"archived":false,"bookmarked":null,"liked":null,"tags":[],"tags_descriptions":{},"views":535,"like_count":1,"has_summary":false,"last_poster_username":"0x1f","category_id":16,"pinned_globally":false,"featured_link":null,"posters":[{"extras":null,"description":"Original Poster","user_id":6259,"primary_group_id":null,"flair_group_id":null},{"extras":null,"description":"Frequent Poster","user_id":3,"primary_group_id":null,"flair_group_id":null},{"extras":"latest","description":"Most Recent Poster","user_id":6441,"primary_group_id":null,"flair_group_id":null}]},{"id":13535,"title":"verify virtualbox","fancy_title":"verify virtualbox","slug":"verify-virtualbox","posts_count":5,"reply_count":1,"highest_post_number":5,"image_url":null,"created_at":"2022-04-07T17:31:07.141Z","last_posted_at":"2022-06-27T23:04:58.975Z","bumped":true,"bumped_at":"2022-06-27T23:04:58.975Z","archetype":"regular","unseen":false,"pinned":false,"unpinned":null,"excerpt":"Hello i’m trying to verify virtualbox download, sha256sum is fine and i have imported public key but i don’t find the signed file anywhere. \nDoes anyone know where is that signed file? if there is one?","visible":true,"closed":false,"archived":false,"bookmarked":null,"liked":null,"tags":[],"tags_descriptions":{},"views":476,"like_count":1,"has_summary":false,"last_poster_username":"0x1f","category_id":16,"pinned_globally":false,"featured_link":null,"posters":[{"extras":null,"description":"Original Poster","user_id":6304,"primary_group_id":null,"flair_group_id":null},{"extras":null,"description":"Frequent Poster","user_id":6141,"primary_group_id":null,"flair_group_id":null},{"extras":null,"description":"Frequent Poster","user_id":3,"primary_group_id":null,"flair_group_id":null},{"extras":"latest","description":"Most Recent Poster","user_id":6441,"primary_group_id":null,"flair_group_id":null}]},{"id":13799,"title":"[solved] swap-file-creator breaks with Whonix 16 for VirtualBox and newer Linux host kernel version 5.18","fancy_title":"[solved] swap-file-creator breaks with Whonix 16 for VirtualBox and newer Linux host kernel version 5.18","slug":"solved-swap-file-creator-breaks-with-whonix-16-for-virtualbox-and-newer-linux-host-kernel-version-5-18","posts_count":6,"reply_count":0,"highest_post_number":6,"image_url":"//forums.whonix.org/uploads/default/optimized/2X/6/694af8fb74342a848d9fae832ba028c481e18a72_2_1024x597.png","created_at":"2022-06-15T21:07:41.479Z","last_posted_at":"2022-06-17T07:42:58.971Z","bumped":true,"bumped_at":"2022-06-17T07:45:18.261Z","archetype":"regular","unseen":false,"pinned":false,"unpinned":null,"excerpt":"Whonix vbox getting this error at the moment: (looks different message from the above post error) \n  \nAnd by this error whonix wont load (only black screen). \nNote: vbox (virtualbox-dkms,virtualbox-qt,virtualbox) install&hellip;","visible":true,"closed":false,"archived":false,"bookmarked":null,"liked":null,"tags":[],"tags_descriptions":{},"views":390,"like_count":3,"has_summary":false,"last_poster_username":"Patrick","category_id":16,"pinned_globally":false,"featured_link":null,"posters":[{"extras":null,"description":"Original Poster","user_id":410,"primary_group_id":null,"flair_group_id":null},{"extras":"latest","description":"Most Recent Poster","user_id":3,"primary_group_id":null,"flair_group_id":null}]},{"id":5184,"title":"Whonix Failed to start Encrypted Swap File Creator","fancy_title":"Whonix Failed to start Encrypted Swap File Creator","slug":"whonix-failed-to-start-encrypted-swap-file-creator","posts_count":4,"reply_count":6,"highest_post_number":4,"image_url":"//forums.whonix.org/uploads/default/optimized/2X/e/ec258fe0a5daac33ba1bcf151eb2d98bee691709_2_1023x576.png","created_at":"2018-05-09T09:00:36.016Z","last_posted_at":"2022-06-17T07:45:18.108Z","bumped":true,"bumped_at":"2022-06-17T07:42:58.971Z","archetype":"regular","unseen":false,"pinned":false,"unpinned":null,"excerpt":"Hello everyone, \nWhen I start whonix it fails to start encrypted Swap File Creator both in the Gateway and the Workstation… \n[Sans%20titre] \nI have haveged installed, and  this problem persist on every reboot. \nAny idea &hellip;","visible":true,"closed":false,"archived":false,"bookmarked":null,"liked":null,"tags":[],"tags_descriptions":{},"views":1989,"like_count":0,"has_summary":false,"last_poster_username":"Patrick","category_id":16,"pinned_globally":false,"featured_link":null,"posters":[{"extras":null,"description":"Original Poster","user_id":3765,"primary_group_id":null,"flair_group_id":null},{"extras":"latest","description":"Most Recent Poster","user_id":3,"primary_group_id":null,"flair_group_id":null}]},{"id":13728,"title":"(Still Unsolved)While taking off. The power went off. Now Whonix is always off","fancy_title":"(Still Unsolved)While taking off. The power went off. Now Whonix is always off","slug":"still-unsolved-while-taking-off-the-power-went-off-now-whonix-is-always-off","posts_count":11,"reply_count":4,"highest_post_number":11,"image_url":null,"created_at":"2022-05-31T17:24:29.282Z","last_posted_at":"2022-06-02T11:57:30.381Z","bumped":true,"bumped_at":"2022-06-02T11:57:30.381Z","archetype":"regular","unseen":false,"pinned":false,"unpinned":null,"excerpt":"Hi gents \nWhen I started Whonix from VirtualBox and before it to start completely \nThe power went out and my PC turned off suddenly \nNow \nMy VMs (same disk, same folder) including Whonix Gateway and Workstation show as “&hellip;","visible":true,"closed":false,"archived":false,"bookmarked":null,"liked":null,"tags":[],"tags_descriptions":{},"views":425,"like_count":2,"has_summary":false,"last_poster_username":"TNT_BOM_BOM","category_id":16,"pinned_globally":false,"featured_link":null,"posters":[{"extras":null,"description":"Original Poster","user_id":6390,"primary_group_id":null,"flair_group_id":null},{"extras":null,"description":"Frequent Poster","user_id":3,"primary_group_id":null,"flair_group_id":null},{"extras":"latest","description":"Most Recent Poster","user_id":410,"primary_group_id":null,"flair_group_id":null}]},{"id":13715,"title":"VBox \"Host I/O Cache\" question","fancy_title":"VBox &ldquo;Host I/O Cache&rdquo; question","slug":"vbox-host-i-o-cache-question","posts_count":2,"reply_count":0,"highest_post_number":2,"image_url":null,"created_at":"2022-05-28T19:23:24.106Z","last_posted_at":"2022-05-29T13:25:18.641Z","bumped":true,"bumped_at":"2022-05-29T13:25:18.641Z","archetype":"regular","unseen":false,"pinned":false,"unpinned":null,"excerpt":"From security perspective, is it safe to enable this option in virtualbox or is it a security risk, better keep it disabled?","visible":true,"closed":false,"archived":false,"bookmarked":null,"liked":null,"tags":[],"tags_descriptions":{},"views":406,"like_count":0,"has_summary":false,"last_poster_username":"Patrick","category_id":16,"pinned_globally":false,"featured_link":null,"posters":[{"extras":null,"description":"Original Poster","user_id":4231,"primary_group_id":null,"flair_group_id":null},{"extras":"latest","description":"Most Recent Poster","user_id":3,"primary_group_id":null,"flair_group_id":null}]},{"id":13697,"title":"sdwdate on old version workstation","fancy_title":"sdwdate on old version workstation","slug":"sdwdate-on-old-version-workstation","posts_count":2,"reply_count":0,"highest_post_number":2,"image_url":null,"created_at":"2022-05-22T10:45:14.789Z","last_posted_at":"2022-05-22T15:08:14.330Z","bumped":true,"bumped_at":"2022-05-22T15:08:14.330Z","archetype":"regular","unseen":false,"pinned":false,"unpinned":null,"excerpt":"hi, at first sorry for my english and propaply stupid question. I’m using old version workstation - 4.19.0.9, and from today (it worked yerstaday) it can’t make sdwdate succes. Initial time fetching in progress all time.&hellip;","visible":true,"closed":false,"archived":false,"bookmarked":null,"liked":null,"tags":[],"tags_descriptions":{},"views":422,"like_count":0,"has_summary":false,"last_poster_username":"Patrick","category_id":16,"pinned_globally":false,"featured_link":null,"posters":[{"extras":null,"description":"Original Poster","user_id":6378,"primary_group_id":null,"flair_group_id":null},{"extras":"latest","description":"Most Recent Poster","user_id":3,"primary_group_id":null,"flair_group_id":null}]},{"id":8021,"title":"Serial Console in VirtualBox","fancy_title":"Serial Console in VirtualBox","slug":"serial-console-in-virtualbox","posts_count":16,"reply_count":4,"highest_post_number":16,"image_url":null,"created_at":"2019-09-05T05:00:56.502Z","last_posted_at":"2022-05-17T09:43:58.231Z","bumped":true,"bumped_at":"2022-05-17T09:43:58.231Z","archetype":"regular","unseen":false,"pinned":false,"unpinned":null,"excerpt":"Serial console works for Whonix KVM. \nPackage serial-console-enable might help / simplify setting up the kernel boot parameters inside the VM. \nsudo apt-get install serial-console-enable\n\nSee also: \nhttps://forums.whonix&hellip;","visible":true,"closed":false,"archived":false,"bookmarked":null,"liked":null,"tags":[],"tags_descriptions":{},"views":2192,"like_count":9,"has_summary":false,"last_poster_username":"Patrick","category_id":16,"pinned_globally":false,"featured_link":null,"posters":[{"extras":"latest","description":"Original Poster, Most Recent Poster","user_id":3,"primary_group_id":null,"flair_group_id":null},{"extras":null,"description":"Frequent Poster","user_id":75,"primary_group_id":null,"flair_group_id":null},{"extras":null,"description":"Frequent Poster","user_id":410,"primary_group_id":null,"flair_group_id":null},{"extras":null,"description":"Frequent Poster","user_id":4609,"primary_group_id":null,"flair_group_id":null},{"extras":null,"description":"Frequent Poster","user_id":4419,"primary_group_id":null,"flair_group_id":null}]},{"id":13568,"title":"install .deb packege","fancy_title":"install .deb packege","slug":"install-deb-packege","posts_count":3,"reply_count":0,"highest_post_number":3,"image_url":null,"created_at":"2022-04-16T20:31:52.682Z","last_posted_at":"2022-04-19T06:28:56.695Z","bumped":true,"bumped_at":"2022-04-19T06:28:56.695Z","archetype":"regular","unseen":false,"pinned":false,"unpinned":null,"excerpt":"Hello community \nI am newbie here. how is possible to install .deb package which i have downloaded? \nThanks in advanced.","visible":true,"closed":false,"archived":false,"bookmarked":null,"liked":null,"tags":[],"tags_descriptions":{},"views":484,"like_count":0,"has_summary":false,"last_poster_username":"Patrick","category_id":16,"pinned_globally":false,"featured_link":null,"posters":[{"extras":null,"description":"Original Poster","user_id":6322,"primary_group_id":null,"flair_group_id":null},{"extras":null,"description":"Frequent Poster","user_id":410,"primary_group_id":null,"flair_group_id":null},{"extras":"latest","description":"Most Recent Poster","user_id":3,"primary_group_id":null,"flair_group_id":null}]}]}}